hyo2.grids-3.2.5-py3.8-nspkg.pth
hyo2/grids/__init__.py
hyo2/grids/_bag2.pyd
hyo2/grids/_gappy.pyd
hyo2/grids/_grids.pyd
hyo2/grids/bag.dll
hyo2/grids/bag2.py
hyo2/grids/beecrypt.dll
hyo2/grids/csar2.py
hyo2/grids/gappy.py
hyo2/grids/grids.py
hyo2/grids/grids_manager.py
hyo2/grids/kluster_grid.py
hyo2/grids/common/default_logging.py
hyo2/grids/common/gdal_aux.py
hyo2/grids/common/helper.py
hyo2/grids/common/testing.py
hyo2/grids/configdata/ellips.dat
hyo2/grids/configdata/ISO19139/bag/bag.xsd
hyo2/grids/configdata/ISO19139/bag/bagCodelists.xml
hyo2/grids/configdata/ISO19139/bag/extension.xsd
hyo2/grids/configdata/ISO19139/gco/basicTypes.xsd
hyo2/grids/configdata/ISO19139/gco/gco.xsd
hyo2/grids/configdata/ISO19139/gco/gcoBase.xsd
hyo2/grids/configdata/ISO19139/gco/readme.txt
hyo2/grids/configdata/ISO19139/gmd/applicationSchema.xsd
hyo2/grids/configdata/ISO19139/gmd/citation.xsd
hyo2/grids/configdata/ISO19139/gmd/constraints.xsd
hyo2/grids/configdata/ISO19139/gmd/content.xsd
hyo2/grids/configdata/ISO19139/gmd/dataQuality.xsd
hyo2/grids/configdata/ISO19139/gmd/distribution.xsd
hyo2/grids/configdata/ISO19139/gmd/extent.xsd
hyo2/grids/configdata/ISO19139/gmd/freeText.xsd
hyo2/grids/configdata/ISO19139/gmd/gmd.xsd
hyo2/grids/configdata/ISO19139/gmd/identification.xsd
hyo2/grids/configdata/ISO19139/gmd/maintenance.xsd
hyo2/grids/configdata/ISO19139/gmd/metadataApplication.xsd
hyo2/grids/configdata/ISO19139/gmd/metadataEntity.xsd
hyo2/grids/configdata/ISO19139/gmd/metadataExtension.xsd
hyo2/grids/configdata/ISO19139/gmd/portrayalCatalogue.xsd
hyo2/grids/configdata/ISO19139/gmd/readme.txt
hyo2/grids/configdata/ISO19139/gmd/referenceSystem.xsd
hyo2/grids/configdata/ISO19139/gmd/spatialRepresentation.xsd
hyo2/grids/configdata/ISO19139/gmi/acquisitionInformation.xsd
hyo2/grids/configdata/ISO19139/gmi/contentInformation.xsd
hyo2/grids/configdata/ISO19139/gmi/dataQualityInformation.xsd
hyo2/grids/configdata/ISO19139/gmi/gmi.xsd
hyo2.grids-3.2.5.dist-info/AUTHORS.rst
hyo2.grids-3.2.5.dist-info/LICENSE
hyo2.grids-3.2.5.dist-info/METADATA
hyo2.grids-3.2.5.dist-info/WHEEL
hyo2.grids-3.2.5.dist-info/entry_points.txt
hyo2.grids-3.2.5.dist-info/namespace_packages.txt
hyo2.grids-3.2.5.dist-info/top_level.txt
hyo2.grids-3.2.5.dist-info/RECORD
